hanzo_tools/__init__.py
hanzo_tools/mcp_tools/__init__.py
hanzo_tools/mcp_tools/mcp_add.py
hanzo_tools/mcp_tools/mcp_remove.py
hanzo_tools/mcp_tools/mcp_stats.py
hanzo_tools/mcp_tools/mcp_tool.py
hanzo_tools_mcp-0.2.0.dist-info/METADATA
hanzo_tools_mcp-0.2.0.dist-info/WHEEL
hanzo_tools_mcp-0.2.0.dist-info/entry_points.txt
hanzo_tools_mcp-0.2.0.dist-info/top_level.txt
hanzo_tools_mcp-0.2.0.dist-info/RECORD
